alma_cdk/cross_region_parameter/__init__.py
alma_cdk/cross_region_parameter/py.typed
alma_cdk/cross_region_parameter/_jsii/__init__.py
alma_cdk/cross_region_parameter/_jsii/cross-region-parameter@0.0.14.jsii.tgz
alma_cdk.cross_region_parameter-0.0.14.dist-info/LICENSE
alma_cdk.cross_region_parameter-0.0.14.dist-info/METADATA
alma_cdk.cross_region_parameter-0.0.14.dist-info/WHEEL
alma_cdk.cross_region_parameter-0.0.14.dist-info/top_level.txt
alma_cdk.cross_region_parameter-0.0.14.dist-info/RECORD
