Metadata-Version: 2.1
Name: alma-cdk.cross-region-parameter
Version: 0.0.14
Summary: Store AWS SSM Parameter Store Parameters into another AWS Region with AWS CDK
Home-page: https://github.com/alma-cdk/cross-region-parameter.git
Author: Alma Media<opensource@almamedia.dev>
License: Apache-2.0
Project-URL: Source, https://github.com/alma-cdk/cross-region-parameter.git
Platform: UNKNOWN
Classifier: Intended Audience :: Developers
Classifier: Operating System :: OS Independent
Classifier: Programming Language :: JavaScript
Classifier: Programming Language :: Python :: 3 :: Only
Classifier: Programming Language :: Python :: 3.7
Classifier: Programming Language :: Python :: 3.8
Classifier: Programming Language :: Python :: 3.9
Classifier: Programming Language :: Python :: 3.10
Classifier: Typing :: Typed
Classifier: Development Status :: 4 - Beta
Classifier: License :: OSI Approved
Requires-Python: ~=3.7
License-File: LICENSE
Requires-Dist: aws-cdk-lib (<3.0.0,>=2.24.1)
Requires-Dist: constructs (<11.0.0,>=10.0.0)
Requires-Dist: jsii (<2.0.0,>=1.70.0)
Requires-Dist: publication (>=0.0.3)
Requires-Dist: typeguard (~=2.13.3)
